DrissionPage/__init__.py
DrissionPage/__init__.pyi
DrissionPage/common.py
DrissionPage/errors.py
DrissionPage/items.py
DrissionPage/version.py
DrissionPage/_base/base.py
DrissionPage/_base/base.pyi
DrissionPage/_base/chromium.py
DrissionPage/_base/chromium.pyi
DrissionPage/_base/driver.py
DrissionPage/_base/driver.pyi
DrissionPage/_configs/chromium_options.py
DrissionPage/_configs/chromium_options.pyi
DrissionPage/_configs/configs.ini
DrissionPage/_configs/options_manage.py
DrissionPage/_configs/options_manage.pyi
DrissionPage/_configs/session_options.py
DrissionPage/_configs/session_options.pyi
DrissionPage/_elements/chromium_element.py
DrissionPage/_elements/chromium_element.pyi
DrissionPage/_elements/none_element.py
DrissionPage/_elements/none_element.pyi
DrissionPage/_elements/session_element.py
DrissionPage/_elements/session_element.pyi
DrissionPage/_functions/browser.py
DrissionPage/_functions/browser.pyi
DrissionPage/_functions/by.py
DrissionPage/_functions/cli.py
DrissionPage/_functions/cookies.py
DrissionPage/_functions/cookies.pyi
DrissionPage/_functions/elements.py
DrissionPage/_functions/elements.pyi
DrissionPage/_functions/keys.py
DrissionPage/_functions/keys.pyi
DrissionPage/_functions/locator.py
DrissionPage/_functions/locator.pyi
DrissionPage/_functions/settings.py
DrissionPage/_functions/settings.pyi
DrissionPage/_functions/suffixes.dat
DrissionPage/_functions/texts.py
DrissionPage/_functions/tools.py
DrissionPage/_functions/tools.pyi
DrissionPage/_functions/web.py
DrissionPage/_functions/web.pyi
DrissionPage/_pages/chromium_base.py
DrissionPage/_pages/chromium_base.pyi
DrissionPage/_pages/chromium_frame.py
DrissionPage/_pages/chromium_frame.pyi
DrissionPage/_pages/chromium_page.py
DrissionPage/_pages/chromium_page.pyi
DrissionPage/_pages/chromium_tab.py
DrissionPage/_pages/chromium_tab.pyi
DrissionPage/_pages/mix_tab.py
DrissionPage/_pages/mix_tab.pyi
DrissionPage/_pages/session_page.py
DrissionPage/_pages/session_page.pyi
DrissionPage-4.1.1.1.dist-info/LICENSE
DrissionPage-4.1.1.1.dist-info/METADATA
DrissionPage-4.1.1.1.dist-info/WHEEL
DrissionPage-4.1.1.1.dist-info/entry_points.txt
DrissionPage-4.1.1.1.dist-info/top_level.txt
DrissionPage-4.1.1.1.dist-info/RECORD
