Metadata-Version: 2.1
Name: DrissionPage
Version: 4.1.1.1
Summary: Python based web automation tool. It can control the browser and send and receive data packets.
Home-page: https://DrissionPage.cn
Author: g1879
Author-email: g1879@qq.com
Keywords: DrissionPage
Classifier: Programming Language :: Python :: 3.6
Classifier: Development Status :: 4 - Beta
Classifier: Topic :: Utilities
Requires-Python: >=3.6
License-File: LICENSE
Requires-Dist: lxml
Requires-Dist: requests
Requires-Dist: cssselect
Requires-Dist: DownloadKit>=2.0.7
Requires-Dist: websocket-client
Requires-Dist: click
Requires-Dist: tldextract>=3.4.4
Requires-Dist: psutil
